{
  "timestamp": "2026-02-06T13:48:29.901487",
  "players": [
    {
      "name": "AI Player 1",
      "total_score": 0,
      "hand": {
        "top": [
          "10C",
          "9C",
          "8S"
        ],
        "middle": [
          "AH",
          "JS",
          "QS",
          "QC",
          "9S"
        ],
        "bottom": [
          "3D",
          "7C",
          "10D",
          "6H",
          "JH"
        ]
      },
      "is_ai": true,
      "fantasy_mode": false
    },
    {
      "name": "AI Player 2",
      "total_score": 0,
      "hand": {
        "top": [
          "KC",
          "6D",
          "4H"
        ],
        "middle": [
          "8D",
          "7H",
          "5C",
          "8H",
          "8C"
        ],
        "bottom": [
          "4C",
          "7S",
          "4D",
          "KS",
          "JC"
        ]
      },
      "is_ai": true,
      "fantasy_mode": false
    }
  ],
  "game_details": {
    "fantasy_mode": false,
    "player_count": 2
  }
}