{
  "timestamp": "2026-02-06T13:52:15.607548",
  "players": [
    {
      "name": "AI Player 1",
      "total_score": 0,
      "hand": {
        "top": [
          "AD",
          "7D",
          "7C"
        ],
        "middle": [
          "3C",
          "4D",
          "3S",
          "8D",
          "8C"
        ],
        "bottom": [
          "JC",
          "10C",
          "4H",
          "KS",
          "10S"
        ]
      },
      "is_ai": true,
      "fantasy_mode": false
    },
    {
      "name": "AI Player 2",
      "total_score": 0,
      "hand": {
        "top": [
          "AH",
          "QH",
          "2C"
        ],
        "middle": [
          "JD",
          "5H",
          "AS",
          "9C",
          "3D"
        ],
        "bottom": [
          "9H",
          "6H",
          "3H",
          "AC",
          "5C"
        ]
      },
      "is_ai": true,
      "fantasy_mode": false
    }
  ],
  "game_details": {
    "fantasy_mode": false,
    "player_count": 2
  }
}