{
  "timestamp": "2026-02-06T13:50:38.912474",
  "players": [
    {
      "name": "AI Player 1",
      "total_score": 0,
      "hand": {
        "top": [
          "AS",
          "AD",
          "9C"
        ],
        "middle": [
          "4D",
          "3C",
          "10C",
          "6D",
          "3D"
        ],
        "bottom": [
          "2C",
          "JH",
          "6C",
          "6H",
          "8D"
        ]
      },
      "is_ai": true,
      "fantasy_mode": false
    },
    {
      "name": "AI Player 2",
      "total_score": 0,
      "hand": {
        "top": [
          "AH",
          "KS",
          "JS"
        ],
        "middle": [
          "7C",
          "5H",
          "QS",
          "JD",
          "2D"
        ],
        "bottom": [
          "QC",
          "JC",
          "4H",
          "AC",
          "10H"
        ]
      },
      "is_ai": true,
      "fantasy_mode": false
    }
  ],
  "game_details": {
    "fantasy_mode": false,
    "player_count": 2
  }
}