{
  "timestamp": "2026-02-06T13:52:17.989389",
  "players": [
    {
      "name": "AI Player 1",
      "total_score": 0,
      "hand": {
        "top": [
          "QH",
          "10S",
          "7D"
        ],
        "middle": [
          "6C",
          "4H",
          "KS",
          "10C",
          "8C"
        ],
        "bottom": [
          "KC",
          "2H",
          "4C",
          "JC",
          "7H"
        ]
      },
      "is_ai": true,
      "fantasy_mode": false
    },
    {
      "name": "AI Player 2",
      "total_score": 0,
      "hand": {
        "top": [
          "QD",
          "AC",
          "9S"
        ],
        "middle": [
          "JH",
          "9D",
          "8H",
          "5H",
          "10H"
        ],
        "bottom": [
          "3C",
          "AD",
          "4D",
          "QS",
          "KD"
        ]
      },
      "is_ai": true,
      "fantasy_mode": false
    }
  ],
  "game_details": {
    "fantasy_mode": false,
    "player_count": 2
  }
}