{
  "timestamp": "2026-02-06T14:03:19.886078",
  "players": [
    {
      "name": "AI Player 1",
      "total_score": 0,
      "hand": {
        "top": [
          "QS",
          "JS",
          "8S"
        ],
        "middle": [
          "KH",
          "KC",
          "9H",
          "8H",
          "JC"
        ],
        "bottom": [
          "5C",
          "5H",
          "10C",
          "2H",
          "AC"
        ]
      },
      "is_ai": true,
      "fantasy_mode": false
    },
    {
      "name": "AI Player 2",
      "total_score": 0,
      "hand": {
        "top": [
          "AH",
          "7H",
          "6S"
        ],
        "middle": [
          "5D",
          "4S",
          "9D",
          "6D",
          "4H"
        ],
        "bottom": [
          "JD",
          "6C",
          "10D",
          "8C",
          "4C"
        ]
      },
      "is_ai": true,
      "fantasy_mode": false
    }
  ],
  "game_details": {
    "fantasy_mode": false,
    "player_count": 2
  }
}