{
  "timestamp": "2026-02-06T13:53:12.817888",
  "players": [
    {
      "name": "AI Player 1",
      "total_score": 0,
      "hand": {
        "top": [
          "AD",
          "AC",
          "10H"
        ],
        "middle": [
          "10C",
          "2S",
          "10D",
          "7D",
          "10S"
        ],
        "bottom": [
          "7C",
          "6H",
          "2C",
          "KS",
          "5H"
        ]
      },
      "is_ai": true,
      "fantasy_mode": false
    },
    {
      "name": "AI Player 2",
      "total_score": 0,
      "hand": {
        "top": [
          "AS",
          "3D",
          "QS"
        ],
        "middle": [
          "JS",
          "JH",
          "4H",
          "3C",
          "6S"
        ],
        "bottom": [
          "7S",
          "8C",
          "2D",
          "KC",
          "QD"
        ]
      },
      "is_ai": true,
      "fantasy_mode": false
    }
  ],
  "game_details": {
    "fantasy_mode": false,
    "player_count": 2
  }
}