{
  "timestamp": "2026-02-06T13:34:12.604637",
  "players": [
    {
      "name": "AI Player 1",
      "total_score": 0,
      "hand": {
        "top": [
          "KH",
          "6D",
          "5S"
        ],
        "middle": [
          "JD",
          "10D",
          "7C",
          "4D",
          "2H"
        ],
        "bottom": [
          "10C",
          "7S",
          "KC",
          "AS",
          "JH"
        ]
      },
      "is_ai": true,
      "fantasy_mode": false
    },
    {
      "name": "AI Player 2",
      "total_score": 0,
      "hand": {
        "top": [
          "AD",
          "2S",
          "KD"
        ],
        "middle": [
          "9S",
          "9D",
          "8D",
          "QC",
          "9H"
        ],
        "bottom": [
          "5D",
          "5C",
          "3H",
          "10H",
          "QS"
        ]
      },
      "is_ai": true,
      "fantasy_mode": false
    }
  ],
  "game_details": {
    "fantasy_mode": false,
    "player_count": 2
  }
}