{
  "timestamp": "2026-02-07T12:16:40.033448",
  "players": [
    {
      "name": "AI Player 1",
      "total_score": 0,
      "hand": {
        "top": [
          "6C",
          "AC",
          "JH"
        ],
        "middle": [
          "4H",
          "10D",
          "JC",
          "3C",
          "JD"
        ],
        "bottom": [
          "AS",
          "6S",
          "QD",
          "6H",
          "3S"
        ]
      },
      "is_ai": true,
      "fantasy_mode": false
    },
    {
      "name": "AI Player 2",
      "total_score": 0,
      "hand": {
        "top": [
          "QH",
          "4C",
          "QS"
        ],
        "middle": [
          "5D",
          "QC",
          "9H",
          "5C",
          "3H"
        ],
        "bottom": [
          "KS",
          "KD",
          "KC",
          "9S",
          "6D"
        ]
      },
      "is_ai": true,
      "fantasy_mode": false
    }
  ],
  "game_details": {
    "fantasy_mode": false,
    "player_count": 2
  }
}