{
  "timestamp": "2026-02-06T14:09:55.809743",
  "players": [
    {
      "name": "AI Player 1",
      "total_score": 0,
      "hand": {
        "top": [
          "KD",
          "JS",
          "7D"
        ],
        "middle": [
          "6C",
          "9D",
          "5S",
          "6H",
          "7C"
        ],
        "bottom": [
          "4S",
          "2C",
          "3H",
          "3D",
          "6S"
        ]
      },
      "is_ai": true,
      "fantasy_mode": false
    },
    {
      "name": "AI Player 2",
      "total_score": 0,
      "hand": {
        "top": [
          "AH",
          "JD",
          "JC"
        ],
        "middle": [
          "7H",
          "4C",
          "KH",
          "QH",
          "JH"
        ],
        "bottom": [
          "KS",
          "10C",
          "3C",
          "5H",
          "10S"
        ]
      },
      "is_ai": true,
      "fantasy_mode": false
    }
  ],
  "game_details": {
    "fantasy_mode": false,
    "player_count": 2
  }
}