{
  "timestamp": "2026-02-05T17:02:38.494714",
  "players": [
    {
      "name": "玩家a",
      "total_score": 8,
      "hand": {
        "top": [
          "K♦",
          "Q♦",
          "A♠"
        ],
        "middle": [
          "6♠",
          "2♣",
          "6♥",
          "2♥",
          "J♥"
        ],
        "bottom": [
          "10♠",
          "J♦",
          "9♥",
          "8♥",
          "Q♥"
        ]
      },
      "is_ai": false,
      "fantasy_mode": false
    },
    {
      "name": "AI (中等)",
      "total_score": 0,
      "hand": {
        "top": [
          "5♦",
          "3♥",
          "2♠"
        ],
        "middle": [
          "6♦",
          "Q♠",
          "J♣",
          "A♦",
          "4♠"
        ],
        "bottom": [
          "A♣",
          "K♥",
          "J♠",
          "10♦",
          "4♥"
        ]
      },
      "is_ai": true,
      "fantasy_mode": false
    }
  ],
  "game_details": {
    "fantasy_mode": false,
    "player_count": 2
  }
}